{
  "$schema": "https://mintlify.com/docs.json",
  "theme": "palm",
  "name": "Thred Docs",
  "colors": {
    "primary": "#0D9373"
  },
  "navigation": {
    "groups": [
      {
        "group": "Getting Started",
        "pages": [
          "getting-started/untitled-page",
          "getting-started/fetch-leads",
          "getting-started/get-enriched-chat-from-customer"
        ]
      }
    ]
  },
  "favicon": "/images/icon.ico",
  "logo": {
    "light": "/images/logo_full_dark.png",
    "dark": "/images/logo_full_light.png"
  }
}